CHANGELOG.txt
LICENSE.txt
MANIFEST.in
README.md
requirements.txt
setup.py
bin/domains
bin/domainsd
domains_api/__init__.py
domains_api/__main__.py
domains_api/arg_parser.py
domains_api/async_runner.py
domains_api/cli_funcs.py
domains_api/constants.py
domains_api/encrypter.py
domains_api/exceptions.py
domains_api/file_handlers.py
domains_api/ip_changer.py
domains_api/user.py
domains_api/version.txt
domains_api.egg-info/PKG-INFO
domains_api.egg-info/SOURCES.txt
domains_api.egg-info/dependency_links.txt
domains_api.egg-info/requires.txt
domains_api.egg-info/top_level.txt