Metadata-Version: 2.1
Name: domains-api
Version: 0.4.2
Summary: Auto-updates dynamic DNS rules on Google Domains (domains.google.com)
Home-page: https://github.com/nihilok/domains-api
Author: Michael Jarvis
Author-email: mjfullstack@gmail.com
License: UNKNOWN
Platform: UNKNOWN
Classifier: Development Status :: 4 - Beta
Classifier: Intended Audience :: Developers
Classifier: Operating System :: OS Independent
Classifier: License :: OSI Approved :: MIT License
Classifier: Programming Language :: Python :: 3
License-File: LICENSE.txt
